shops_payment_processing/__init__.py
shops_payment_processing/__init__.pyi
shops_payment_processing/handlers/__init__.py
shops_payment_processing/handlers/__init__.pyi
shops_payment_processing/handlers/invoice_creation.py
shops_payment_processing/handlers/invoice_creation.pyi
shops_payment_processing/logging_config.py
shops_payment_processing/logging_config.pyi
shops_payment_processing/models/__init__.py
shops_payment_processing/models/__init__.pyi
shops_payment_processing/models/invoice.py
shops_payment_processing/models/invoice.pyi
shops_payment_processing/models/order.py
shops_payment_processing/models/order.pyi
shops_payment_processing/models/payment.py
shops_payment_processing/models/payment.pyi
shops_payment_processing/models/shop.py
shops_payment_processing/models/shop.pyi
shops_payment_processing/models/user.py
shops_payment_processing/models/user.pyi
shops_payment_processing/services/__init__.py
shops_payment_processing/services/__init__.pyi
shops_payment_processing/services/life_pay.py
shops_payment_processing/services/life_pay.pyi
shops_payment_processing/services/tkassa.py
shops_payment_processing/services/tkassa.pyi
shops_payment_processing/services/yookassa.py
shops_payment_processing/services/yookassa.pyi
shops_payment_processing/utils/__init__.py
shops_payment_processing/utils/__init__.pyi
shops_payment_processing/utils/link_generation.py
shops_payment_processing/utils/link_generation.pyi
shops_payment_processing-1.1.1.dist-info/METADATA
shops_payment_processing-1.1.1.dist-info/WHEEL
shops_payment_processing-1.1.1.dist-info/RECORD
